__init__.py
main.py
utils.py
fitconnect_cli-0.1.1.dist-info/entry_points.txt
fitconnect_cli-0.1.1.dist-info/LICENSE.md
fitconnect_cli-0.1.1.dist-info/WHEEL
fitconnect_cli-0.1.1.dist-info/METADATA
fitconnect_cli-0.1.1.dist-info/RECORD
