Metadata-Version: 2.1
Name: fitconnect-cli
Version: 0.1.1
Summary: 
Author: Lilith Wittmann
Author-email: mail@lilithwittmann.de
Requires-Python: >=3.6.2,<4.0
Classifier: Programming Language :: Python :: 3
Classifier: Programming Language :: Python :: 3.7
Classifier: Programming Language :: Python :: 3.8
Classifier: Programming Language :: Python :: 3.9
Requires-Dist: PyInquirer (>=1.0.3,<2.0.0)
Requires-Dist: PyJWT (>=2.1.0,<3.0.0)
Requires-Dist: josepy (>=1.8.0,<2.0.0)
Requires-Dist: pem (>=21.2.0,<22.0.0)
Requires-Dist: pyOpenSSL (>=20.0.1,<21.0.0)
Requires-Dist: python-json-config (>=1.2.3,<2.0.0)
Requires-Dist: requests (>=2.25.1,<3.0.0)
